poetry_tutorial_project_doron/__init__.py
poetry_tutorial_project_doron-0.1.0.dist-info/WHEEL
poetry_tutorial_project_doron-0.1.0.dist-info/METADATA
poetry_tutorial_project_doron-0.1.0.dist-info/RECORD
