Metadata-Version: 2.1
Name: poetry-tutorial-project-doron
Version: 0.1.0
Summary: 
Author: dorhar
Author-email: doron.harnoy@tensorleap.ai
Requires-Python: >=3.7,<4.0
Classifier: Programming Language :: Python :: 3
Classifier: Programming Language :: Python :: 3.7
Classifier: Programming Language :: Python :: 3.8
Classifier: Programming Language :: Python :: 3.9
Requires-Dist: icecream (>=2.1.0,<3.0.0)
